coverup/__init__.py
coverup/__main__.py
coverup/__pyinstaller.py
coverup/document_loader.py
coverup/i18n.py
coverup/image_container.py
coverup/main.py
coverup/translations.py
coverup/ui.py
coverup/utils.py
coverup/workfile.py
"coverup/fonts/MaterialSymbolsOutlined[FILL,GRAD,opsz,wght].ttf"
coverup/pyinstaller_hooks/__init__.py
coverup/pyinstaller_hooks/hook-coverup.py
coverup_pdf-0.4.1.dist-info/licenses/LICENSE
coverup_pdf-0.4.1.dist-info/METADATA
coverup_pdf-0.4.1.dist-info/WHEEL
coverup_pdf-0.4.1.dist-info/entry_points.txt
coverup_pdf-0.4.1.dist-info/top_level.txt
coverup_pdf-0.4.1.dist-info/RECORD
