Metadata-Version: 2.4
Name: coverup-pdf
Version: 0.4.1
Summary: A tool for redacting PDF files and images
Author-email: Björn Seipel <support@digidigital.de>
Maintainer-email: Björn Seipel <support@digidigital.de>
License: GPL-3.0
Project-URL: Homepage, https://coverup.digidigital.de
Project-URL: Repository, https://github.com/digidigital/CoverUP
Project-URL: Issues, https://github.com/digidigital/CoverUP/issues
Keywords: pdf,redaction,privacy,image,editor
Classifier: Development Status :: 4 - Beta
Classifier: Environment :: X11 Applications
Classifier: Intended Audience :: End Users/Desktop
Classifier: License :: OSI Approved :: GNU General Public License v3 (GPLv3)
Classifier: Operating System :: OS Independent
Classifier: Programming Language :: Python :: 3
Classifier: Programming Language :: Python :: 3.9
Classifier: Programming Language :: Python :: 3.10
Classifier: Programming Language :: Python :: 3.11
Classifier: Programming Language :: Python :: 3.12
Classifier: Topic :: Multimedia :: Graphics :: Editors
Classifier: Topic :: Office/Business
Classifier: Topic :: Security
Requires-Python: >=3.9
License-File: LICENSE
Requires-Dist: FreeSimpleGUI>=5.0.0
Requires-Dist: pypdfium2>=4.0.0
Requires-Dist: Pillow>=10.0.0
Requires-Dist: fpdf2>=2.7.0
Requires-Dist: appdirs>=1.4.4
Provides-Extra: dev
Requires-Dist: pyinstaller>=5.0.0; extra == "dev"
Requires-Dist: pytest>=7.0.0; extra == "dev"
Dynamic: license-file
